KynlosWebServer/__init__.py
KynlosWebServer/gui.py
KynlosWebServer/main.py
Kynlos_Web_Server-0.1.0.dist-info/METADATA
Kynlos_Web_Server-0.1.0.dist-info/WHEEL
Kynlos_Web_Server-0.1.0.dist-info/entry_points.txt
Kynlos_Web_Server-0.1.0.dist-info/top_level.txt
Kynlos_Web_Server-0.1.0.dist-info/RECORD
