Metadata-Version: 2.1
Name: Kynlos_Web_Server
Version: 0.1.0
Summary: A full-featured web server with PHP support
Home-page: https://github.com/Kynlos/KynlosWebServer
Author: Kynlo Akari
Author-email: kynloakari@gmail.com
Classifier: Programming Language :: Python :: 3
Classifier: License :: OSI Approved :: MIT License
Classifier: Operating System :: OS Independent
Requires-Python: >=3.6
